kwollect/__init__.py
kwollect/kwollector.py
kwollect/kwollector_wattmetre.py
kwollect/db/__init__.py
kwollect/db/kwollect_setup_db.py
kwollect/db/kwollect_setup_db_oar.py
kwollect/db/old
kwollect/grafana/kwollect_dashboard.json
kwollect/grafana/kwollect_dashboard_new.json
kwollect/grafana/kwollect_dashboardsource.yaml
kwollect/grafana/postgres_datasource.yaml
kwollect/tools/__init__.py
kwollect/tools/grafana_dashboard.json
kwollect/tools/kwollect_setup_db.py
kwollect/tools/kwollect_setup_db_oar.py
kwollect-1.3.1.dist-info/LICENSE.txt
kwollect-1.3.1.dist-info/METADATA
kwollect-1.3.1.dist-info/WHEEL
kwollect-1.3.1.dist-info/entry_points.txt
kwollect-1.3.1.dist-info/top_level.txt
kwollect-1.3.1.dist-info/RECORD
