Metadata-Version: 2.1
Name: kwollect
Version: 1.3.1
Summary: Kwollect framework for metrics collection
Home-page: https://gitlab.inria.fr/delamare/kwollect
Author: Simon Delamare
Author-email: simon.delamare@ens-lyon.fr
Classifier: Programming Language :: Python :: 3
Classifier: License :: OSI Approved :: MIT License
Requires-Python: >=3.7
License-File: LICENSE.txt
Requires-Dist: pyonf
Requires-Dist: psycopg2-binary (==2.9.3)
Requires-Dist: PyJWT (>=2)
Requires-Dist: pyyaml
Requires-Dist: asyncpg
Requires-Dist: aiohttp
Requires-Dist: aiosnmp
Requires-Dist: orjson
